textblocks/__init__.py
textblocks-0.0.1.dist-info/METADATA
textblocks-0.0.1.dist-info/WHEEL
textblocks-0.0.1.dist-info/licenses/LICENSE
textblocks-0.0.1.dist-info/RECORD
